[
  {
    "id": 7479,
    "automobile_id": 1620,
    "name": "0.5 4MT (22 HP)",
    "specs": {
      "Engine Specs": {
        "Cylinders:": "L2",
        "Displacement:": "499 Cm3",
        "Power:": "16.2 Kw @ 5500 Rpm\r\n22 Hp @ 5500 Rpm\r\n22 Bhp @ 5500 Rpm",
        "Torque:": "25 Lb-Ft @ 3500 Rpm\r\n34 Nm @ 3500 Rpm",
        "Fuel System:": "Carburetor",
        "Fuel:": "Gasoline"
      },
      "Performance Specs": {
        "Top Speed:": "66 Mph (106 Km/H)",
        "Acceleration 0-62 Mph (0-100 Kph):": "45 S"
      },
      "Transmission Specs": {
        "Drive Type:": "Front Wheel Drive",
        "Gearbox:": "4-Speed Manual"
      },
      "Brakes Specs": {
        "Front:": "Drums",
        "Rear:": "Drums"
      },
      "Tires Specs": {
        "Tire Size:": "125 Sr12"
      },
      "Dimensions": {
        "Length:": "116.1 In (2949 Mm)",
        "Width:": "55.5 In (1410 Mm)",
        "Height:": "53.2 In (1351 Mm)",
        "Front/Rear Track:": "47.2/47.2 In (1,199/1,199 Mm)",
        "Wheelbase:": "75.4 In (1915 Mm)",
        "Ground Clearance:": "5.1 In (130 Mm)",
        "Aerodynamics (Cd):": "0.43"
      },
      "Weight Specs": {
        "Unladen Weight:": "1301 Lbs (590 Kg)",
        "Gross Weight Limit:": "2006 Lbs (910 Kg)"
      },
      "Fuel Economy (Nedc)": {
        "Combined:": "71.3 Mpg Us (3.3 L/100Km)"
      }
    }
  }
]