[
  {
    "id": 5187,
    "automobile_id": 996,
    "name": "3.0L 4MT RWD (81 HP)",
    "specs": {
      "Engine Specs": {
        "Cylinders:": "L8",
        "Displacement:": "2991 Cm3",
        "Power:": "59.7 Kw @ 4000 Rpm\r\n81.1 Hp @ 4000 Rpm\r\n80 Bhp @ 4000 Rpm",
        "Torque:": "114 Lb-Ft @ - Rpm\r\n155 Nm @ - Rpm",
        "Fuel System:": "Carburetor",
        "Fuel:": "Gasoline"
      },
      "Performance Specs": {
        "Top Speed:": "85 Mph (137 Km/H)"
      },
      "Transmission Specs": {
        "Drive Type:": "Rear Wheel Drive",
        "Gearbox:": "4-Speed Manual"
      },
      "Brakes Specs": {
        "Front:": "Drums",
        "Rear:": "Drums"
      },
      "Tires Specs": {
        "Tire Size:": "28 X 4.95"
      },
      "Dimensions": {
        "Front/Rear Track:": "49.2/49.2 In (1,250/1,250 Mm)",
        "Wheelbase:": "122.8 In (3119 Mm)"
      },
      "Weight Specs": {
        "Unladen Weight:": "2403 Lbs (1090 Kg)"
      }
    }
  }
]