[
  {
    "id": 169,
    "automobile_id": 81,
    "name": "1.8L Turbo 6AT (240 HP)",
    "specs": {
      "Engine Specs": {
        "Cylinders:": "L4",
        "Displacement:": "1742 Cm3",
        "Power:": "177 Kw @ 6000 Rpm\r\n240 Hp @ 6000 Rpm\r\n237 Bhp @ 6000 Rpm",
        "Torque:": "236 Lb-Ft @ 2100-3750 Rpm\r\n320 Nm @ 2100-3750 Rpm",
        "Fuel System:": "Turbocharged Direct Injection",
        "Fuel:": "Gasoline"
      },
      "Performance Specs": {
        "Top Speed:": "160 Mph (257 Km/H)",
        "Acceleration 0-62 Mph (0-100 Kph):": "4.5 S"
      },
      "Transmission Specs": {
        "Drive Type:": "Rear Wheel Drive",
        "Gearbox:": "Alfa Tct (Dual Dry Clutch) 6 Speed"
      },
      "Brakes Specs": {
        "Front:": "Self-Ventilating Perforated Discs",
        "Rear:": "Self-Ventilating Perforated Discs"
      },
      "Tires Specs": {
        "Tire Size:": "Front: 205/45 R17; Rear: 235/40 R18"
      },
      "Dimensions": {
        "Length:": "157 In (3988 Mm)",
        "Width:": "73.4 In (1864 Mm)",
        "Height:": "46.6 In (1184 Mm)",
        "Front/Rear Track:": "63.8/63.1 In (1,621/1,603 Mm)",
        "Wheelbase:": "93.7 In (2380 Mm)",
        "Ground Clearance:": "4.5 In (114 Mm)",
        "Cargo Volume:": "3.9 Cuft (110 L)",
        "Aerodynamics (Cd):": "0.33"
      },
      "Weight Specs": {
        "Unladen Weight:": "1973 Lbs (895 Kg)",
        "Gross Weight Limit:": "2840 Lbs (1288 Kg)"
      },
      "Fuel Economy (Nedc)": {
        "City:": "24 Mpg Us (9.8 L/100Km)",
        "Highway:": "47 Mpg Us (5 L/100Km)",
        "Combined:": "34.6 Mpg Us (6.8 L/100Km)",
        "Co2 Emissions:": "157 G/Km"
      }
    }
  }
]