[
  {
    "id": 25561,
    "automobile_id": 6279,
    "name": "2.5L CVT (182 HP)",
    "specs": {
      "Engine Specs": {
        "Cylinders:": "L4",
        "Displacement:": "2498 Cm3",
        "Power:": "133.9 Kw @ 5800 Rpm\r\n182 Hp @ 5800 Rpm\r\n180 Bhp @ 5800 Rpm",
        "Torque:": "176 Lb-Ft @ 4400 Rpm\r\n239 Nm @ 4400 Rpm",
        "Fuel System:": "Direct Injection",
        "Fuel:": "Gasoline"
      },
      "Transmission Specs": {
        "Drive Type:": "All Wheel Drive",
        "Gearbox:": "Cvt"
      },
      "Brakes Specs": {
        "Front:": "Ventilated Discs",
        "Rear:": "Discs"
      },
      "Tires Specs": {
        "Tire Size:": "225/60 R17"
      },
      "Dimensions": {
        "Length:": "182.1 In (4625 Mm)",
        "Width:": "71.5 In (1816 Mm)",
        "Height:": "68.1 In (1730 Mm)",
        "Wheelbase:": "105.1 In (2670 Mm)",
        "Ground Clearance:": "8.7 In (221 Mm)",
        "Cargo Volume:": "76.1 Cuft (2155 L)"
      },
      "Fuel Economy (Nedc)": {
        "Combined:": "33 Mpg Us (7.1 L/100Km)"
      }
    }
  }
]