[
  {
    "id": 18943,
    "automobile_id": 4801,
    "name": "1.2L ECO CVT (79 HP)",
    "specs": {
      "Engine Specs": {
        "Cylinders:": "L3",
        "Displacement:": "1200 Cm3",
        "Power:": "58 Kw @ 6000 Rpm\r\n79 Hp @ 6000 Rpm\r\n78 Bhp @ 6000 Rpm",
        "Torque:": "78 Lb-Ft @ 4400 Rpm\r\n106 Nm @ 4400 Rpm",
        "Fuel System:": "Direct Injection",
        "Fuel:": "Gasoline"
      },
      "Transmission Specs": {
        "Drive Type:": "Front Wheel Drive",
        "Gearbox:": "Manual Or The Xtronic-Cvt"
      },
      "Dimensions": {
        "Length:": "174.17 In (4424 Mm)",
        "Width:": "66.73 In (1695 Mm)",
        "Height:": "59.05 In (1500 Mm)",
        "Wheelbase:": "102.36 In (2600 Mm)",
        "Cargo Volume:": "17.3 Cuft (490 L)",
        "Aerodynamics (Cd):": "0.29"
      },
      "Weight Specs": {
        "Unladen Weight:": "2204 Lbs (1000 Kg)",
        "Gross Weight Limit:": "3306 Lbs (1500 Kg)"
      },
      "Fuel Economy (Nedc)": {
        "Combined:": "47.02 Mpg Us (5 L/100Km)",
        "Co2 Emissions:": "120 G/Km"
      }
    }
  }
]