[
  {
    "id": 13409,
    "automobile_id": 3240,
    "name": "1.0 T-GDI 5MT (100 HP)",
    "specs": {
      "Engine Specs": {
        "Cylinders:": "L3",
        "Displacement:": "998 Cm3",
        "Power:": "73.5 Kw @ 4500 Rpm\r\n100 Hp @ 4500 Rpm\r\n99 Bhp @ 4500 Rpm",
        "Torque:": "127 Lb-Ft @ 1500-4000 Rpm\r\n172 Nm @ 1500-4000 Rpm",
        "Fuel System:": "Turbocharged Direct Injection",
        "Fuel:": "Gasoline"
      },
      "Performance Specs": {
        "Top Speed:": "112 Mph (180 Km/H)",
        "Acceleration 0-62 Mph (0-100 Kph):": "10.1 S"
      },
      "Transmission Specs": {
        "Drive Type:": "Front Wheel Drive",
        "Gearbox:": "5-Speed Manual"
      },
      "Brakes Specs": {
        "Front:": "Ventilated Discs",
        "Rear:": "Drums"
      },
      "Tires Specs": {
        "Tire Size:": "175/65 R14"
      },
      "Dimensions": {
        "Ground Clearance:": "6.1 In (155 Mm)"
      },
      "Fuel Economy (Nedc)": {
        "Combined:": "52.3 Mpg Us (4.5 L/100Km)",
        "Co2 Emissions:": "104 G/Km"
      }
    }
  }
]