[
  {
    "id": 10153,
    "automobile_id": 2352,
    "name": "1.3i 5MT FWD (60 HP)",
    "specs": {
      "Engine Specs": {
        "Cylinders:": "L4",
        "Displacement:": "1299 Cm3",
        "Power:": "44 Kw @ 5000 Rpm\r\n60 Hp @ 5000 Rpm\r\n59 Bhp @ 5000 Rpm",
        "Torque:": "76 Lb-Ft @ 2500 Rpm\r\n103 Nm @ 2500 Rpm",
        "Fuel System:": "Multipoint Injection",
        "Fuel:": "Gasoline",
        "Fuel Capacity:": "10.6 Gallons (40.1 L)"
      },
      "Performance Specs": {
        "Top Speed:": "95.1 Mph (153 Km/H)",
        "Acceleration 0-62 Mph (0-100 Kph):": "16.4 S"
      },
      "Transmission Specs": {
        "Drive Type:": "Front Wheel Drive",
        "Gearbox:": "5-Speed Manual"
      },
      "Brakes Specs": {
        "Front:": "Ventilated Discs",
        "Rear:": "Drums"
      },
      "Tires Specs": {
        "Tire Size:": "165/70Tr13"
      },
      "Dimensions": {
        "Length:": "150.8 In (3830 Mm)",
        "Width:": "64.2 In (1631 Mm)",
        "Height:": "52 In (1321 Mm)",
        "Front/Rear Track:": "56.3/54.3 In (1,430/1,379 Mm)",
        "Wheelbase:": "96.5 In (2451 Mm)",
        "Ground Clearance:": "5.5 In (140 Mm)",
        "Cargo Volume:": "8.8 Cuft (249 L)"
      },
      "Weight Specs": {
        "Unladen Weight:": "2090 Lbs (948 Kg)",
        "Gross Weight Limit:": "3218.7 Lbs (1460 Kg)"
      },
      "Fuel Economy (Nedc)": {
        "City:": "27 Mpg Us (8.7 L/100Km)",
        "Highway:": "39.9 Mpg Us (5.9 L/100Km)",
        "Combined:": "34.1 Mpg Us (6.9 L/100Km)",
        "Co2 Emissions:": "161 G/Km"
      }
    }
  },
  {
    "id": 10154,
    "automobile_id": 2352,
    "name": "1.3i 5MT FWD (75 HP)",
    "specs": {
      "Engine Specs": {
        "Cylinders:": "L4",
        "Displacement:": "1242 Cm3",
        "Power:": "55 Kw @ 5200 Rpm\r\n75 Hp @ 5200 Rpm\r\n74 Bhp @ 5200 Rpm",
        "Torque:": "81 Lb-Ft @ 4000 Rpm\r\n110 Nm @ 4000 Rpm",
        "Fuel System:": "Multipoint Injection",
        "Fuel:": "Gasoline",
        "Fuel Capacity:": "10.6 Gallons (40.1 L)"
      },
      "Performance Specs": {
        "Top Speed:": "103.8 Mph (167 Km/H)",
        "Acceleration 0-62 Mph (0-100 Kph):": "13.1 S"
      },
      "Transmission Specs": {
        "Drive Type:": "Front Wheel Drive",
        "Gearbox:": "5-Speed Manual"
      },
      "Brakes Specs": {
        "Front:": "Ventilated Discs",
        "Rear:": "Drums"
      },
      "Tires Specs": {
        "Tire Size:": "165/70Tr13"
      },
      "Dimensions": {
        "Length:": "150.8 In (3830 Mm)",
        "Width:": "64.2 In (1631 Mm)",
        "Height:": "52 In (1321 Mm)",
        "Front/Rear Track:": "56.3/54.3 In (1,430/1,379 Mm)",
        "Wheelbase:": "96.5 In (2451 Mm)",
        "Ground Clearance:": "5.5 In (140 Mm)",
        "Cargo Volume:": "8.8 Cuft (249 L)"
      },
      "Weight Specs": {
        "Unladen Weight:": "2067.9 Lbs (938 Kg)",
        "Gross Weight Limit:": "3251.8 Lbs (1475 Kg)"
      },
      "Fuel Economy (Nedc)": {
        "City:": "27 Mpg Us (8.7 L/100Km)",
        "Highway:": "40.6 Mpg Us (5.8 L/100Km)",
        "Combined:": "34.1 Mpg Us (6.9 L/100Km)",
        "Co2 Emissions:": "161 G/Km"
      }
    }
  },
  {
    "id": 10155,
    "automobile_id": 2352,
    "name": "1.4i 5MT FWD (90 HP)",
    "specs": {
      "Engine Specs": {
        "Cylinders:": "L4",
        "Displacement:": "1388 Cm3",
        "Power:": "66 Kw @ 5500 Rpm\r\n90 Hp @ 5500 Rpm\r\n89 Bhp @ 5500 Rpm",
        "Torque:": "92 Lb-Ft @ 4500 Rpm\r\n125 Nm @ 4500 Rpm",
        "Fuel System:": "Multipoint Injection",
        "Fuel:": "Gasoline",
        "Fuel Capacity:": "10.6 Gallons (40.1 L)"
      },
      "Performance Specs": {
        "Top Speed:": "110 Mph (177 Km/H)",
        "Acceleration 0-62 Mph (0-100 Kph):": "11.4 S"
      },
      "Transmission Specs": {
        "Drive Type:": "Front Wheel Drive",
        "Gearbox:": "5-Speed Manual"
      },
      "Brakes Specs": {
        "Front:": "Ventilated Discs",
        "Rear:": "Drums"
      },
      "Tires Specs": {
        "Tire Size:": "185/55Hr14"
      },
      "Dimensions": {
        "Length:": "150.8 In (3830 Mm)",
        "Width:": "64.2 In (1631 Mm)",
        "Height:": "52 In (1321 Mm)",
        "Front/Rear Track:": "56.3/54.3 In (1,430/1,379 Mm)",
        "Wheelbase:": "96.5 In (2451 Mm)",
        "Ground Clearance:": "5.5 In (140 Mm)",
        "Cargo Volume:": "8.8 Cuft (249 L)"
      },
      "Weight Specs": {
        "Unladen Weight:": "21756 Lbs (9868 Kg)",
        "Gross Weight Limit:": "3251.8 Lbs (1475 Kg)"
      },
      "Fuel Economy (Nedc)": {
        "City:": "26.7 Mpg Us (8.8 L/100Km)",
        "Highway:": "41.3 Mpg Us (5.7 L/100Km)",
        "Combined:": "34.1 Mpg Us (6.9 L/100Km)",
        "Co2 Emissions:": "161 G/Km"
      }
    }
  },
  {
    "id": 10156,
    "automobile_id": 2352,
    "name": "1.8L D 5MT FWD  (75 HP)",
    "specs": {
      "Engine Specs": {
        "Cylinders:": "L4",
        "Displacement:": "1753 Cm3",
        "Power:": "55 Kw @ 4000 Rpm\r\n75 Hp @ 4000 Rpm\r\n74 Bhp @ 4000 Rpm",
        "Torque:": "103 Lb-Ft @ 1900 Rpm\r\n140 Nm @ 1900 Rpm",
        "Fuel System:": "Direct Injection",
        "Fuel:": "Diesel",
        "Fuel Capacity:": "10.6 Gallons (40.1 L)"
      },
      "Performance Specs": {
        "Top Speed:": "104.4 Mph (168 Km/H)",
        "Acceleration 0-62 Mph (0-100 Kph):": "14.3 S"
      },
      "Transmission Specs": {
        "Drive Type:": "Front Wheel Drive",
        "Gearbox:": "Manual, 5 Speed"
      },
      "Brakes Specs": {
        "Front:": "Ventilated Discs",
        "Rear:": "Drums"
      },
      "Tires Specs": {
        "Tire Size:": "165/70Tr13"
      },
      "Dimensions": {
        "Length:": "150.8 In (3830 Mm)",
        "Width:": "64.2 In (1631 Mm)",
        "Height:": "52 In (1321 Mm)",
        "Front/Rear Track:": "56.3/54.3 In (1,430/1,379 Mm)",
        "Wheelbase:": "96.5 In (2451 Mm)",
        "Ground Clearance:": "5.5 In (140 Mm)",
        "Cargo Volume:": "8.8 Cuft (249 L)"
      },
      "Weight Specs": {
        "Unladen Weight:": "2250.9 Lbs (1021 Kg)",
        "Gross Weight Limit:": "3417.2 Lbs (1550 Kg)"
      },
      "Fuel Economy (Nedc)": {
        "City:": "33.6 Mpg Us (7 L/100Km)",
        "Highway:": "54.7 Mpg Us (4.3 L/100Km)",
        "Combined:": "44.4 Mpg Us (5.3 L/100Km)",
        "Co2 Emissions:": "144 G/Km"
      }
    }
  },
  {
    "id": 10157,
    "automobile_id": 2352,
    "name": "1.8L D 5MT FWD (60 HP)",
    "specs": {
      "Engine Specs": {
        "Cylinders:": "L4",
        "Displacement:": "1753 Cm3",
        "Power:": "44 Kw @ 4800 Rpm\r\n60 Hp @ 4800 Rpm\r\n59 Bhp @ 4800 Rpm",
        "Torque:": "77 Lb-Ft @ 2500 Rpm\r\n105 Nm @ 2500 Rpm",
        "Fuel System:": "Indirect Injection",
        "Fuel:": "Diesel",
        "Fuel Capacity:": "10.6 Gallons (40.1 L)"
      },
      "Performance Specs": {
        "Top Speed:": "96.3 Mph (155 Km/H)",
        "Acceleration 0-62 Mph (0-100 Kph):": "17.5 S"
      },
      "Transmission Specs": {
        "Drive Type:": "Front Wheel Drive",
        "Gearbox:": "5-Speed Manual"
      },
      "Brakes Specs": {
        "Front:": "Ventilated Discs",
        "Rear:": "Drums"
      },
      "Tires Specs": {
        "Tire Size:": "165/70Tr13"
      },
      "Dimensions": {
        "Length:": "150.8 In (3830 Mm)",
        "Width:": "64.2 In (1631 Mm)",
        "Height:": "52 In (1321 Mm)",
        "Front/Rear Track:": "56.3/54.3 In (1,430/1,379 Mm)",
        "Wheelbase:": "96.5 In (2451 Mm)",
        "Ground Clearance:": "5.5 In (140 Mm)",
        "Cargo Volume:": "8.8 Cuft (249 L)"
      },
      "Weight Specs": {
        "Unladen Weight:": "2250.9 Lbs (1021 Kg)",
        "Gross Weight Limit:": "3417.2 Lbs (1550 Kg)"
      },
      "Fuel Economy (Nedc)": {
        "City:": "29.8 Mpg Us (7.9 L/100Km)",
        "Highway:": "47 Mpg Us (5 L/100Km)",
        "Combined:": "38.6 Mpg Us (6.1 L/100Km)",
        "Co2 Emissions:": "161 G/Km"
      }
    }
  }
]