[
  {
    "id": 17930,
    "automobile_id": 4479,
    "name": "4.0L V8 7AT RWD (476 HP)",
    "specs": {
      "Engine Specs": {
        "Cylinders:": "V8",
        "Displacement:": "3982 Cm3",
        "Power:": "350.1 Kw @ 6000 Rpm\r\n476 Hp @ 6000 Rpm\r\n469 Bhp @ 6000 Rpm",
        "Torque:": "465 Lb-Ft @ 1900-5000 Rpm\r\n630 Nm @ 1900-5000 Rpm",
        "Fuel System:": "Turbocharge Direct Injection",
        "Fuel:": "Gasoline"
      },
      "Performance Specs": {
        "Top Speed:": "189 Mph (304 Km/H)",
        "Acceleration 0-62 Mph (0-100 Kph):": "4 S"
      },
      "Transmission Specs": {
        "Drive Type:": "Rear Wheel Drive",
        "Gearbox:": "7-Speed Automatic (Amg Speedshift Dct)"
      },
      "Brakes Specs": {
        "Front:": "Ventilated Discs",
        "Rear:": "Ventilated Discs"
      },
      "Tires Specs": {
        "Tire Size:": "255/35 R 19 || 295/35 R 19"
      },
      "Dimensions": {
        "Length:": "178.9 In (4544 Mm)",
        "Width:": "81.7 In (2075 Mm)",
        "Height:": "50.7 In (1288 Mm)",
        "Front/Rear Track:": "66.3/65 In (1,684/1,651 Mm)",
        "Wheelbase:": "103.5 In (2629 Mm)",
        "Cargo Volume:": "6.2 Cuft (176 L)",
        "Aerodynamics (Cd):": "0.36"
      },
      "Fuel Economy (Nedc)": {
        "Combined:": "20.6 Mpg Us (11.4 L/100Km)",
        "Co2 Emissions:": "261 G/Km"
      }
    }
  }
]