[
  {
    "id": 16967,
    "automobile_id": 4181,
    "name": "6.0 V12 5AT (612 HP)",
    "specs": {
      "Engine Specs": {
        "Cylinders:": "V12",
        "Displacement:": "5980 Cm3",
        "Power:": "450 Kw @ 4800-5100 Rpm\r\n612 Hp @ 4800-5100 Rpm\r\n603 Bhp @ 4800-5100 Rpm",
        "Torque:": "738 Lb-Ft @ 2000-4000 Rpm\r\n1000 Nm @ 2000-4000 Rpm",
        "Fuel System:": "Supercharged Multipoint Injection",
        "Fuel:": "Gasoline"
      },
      "Performance Specs": {
        "Top Speed:": "155.3 Mph (250 Km/H)",
        "Acceleration 0-62 Mph (0-100 Kph):": "4.4 S"
      },
      "Transmission Specs": {
        "Drive Type:": "Rear Wheel Drive",
        "Gearbox:": "5-Speed Automatic"
      },
      "Brakes Specs": {
        "Front:": "Ventilated Discs",
        "Rear:": "Ventilated Discs"
      },
      "Tires Specs": {
        "Tire Size:": "245/35 Zr19 || 275/30 Zr 19"
      },
      "Dimensions": {
        "Length:": "196.6 In (4994 Mm)",
        "Width:": "73.1 In (1857 Mm)",
        "Height:": "55 In (1397 Mm)",
        "Front/Rear Track:": "62.1/62.1 In (1,577/1,577 Mm)",
        "Wheelbase:": "113.6 In (2885 Mm)",
        "Ground Clearance:": "5.1 In (130 Mm)",
        "Cargo Volume:": "15.9 Cuft (450 L)",
        "Aerodynamics (Cd):": "0.29"
      },
      "Weight Specs": {
        "Unladen Weight:": "4530 Lbs (2055 Kg)",
        "Gross Weight Limit:": "5688 Lbs (2580 Kg)"
      },
      "Fuel Economy (Nedc)": {
        "City:": "11.9 Mpg Us (19.8 L/100Km)",
        "Highway:": "24.8 Mpg Us (9.5 L/100Km)",
        "Combined:": "17.8 Mpg Us (13.2 L/100Km)",
        "Co2 Emissions:": "317 G/Km"
      }
    }
  }
]